<?xml version="1.0" encoding="UTF-8"?>
<livro nome="2ª João" abreviatura="2jo" capitulos="1">
	<capitulo numero="1">
		<versiculo numero="1">O ancião à senhora eleita, e a seus filhos, aos quais amo na verdade, e não somente eu, mas também todos os que têm conhecido a verdade,</versiculo>
		<versiculo numero="2">Por amor da verdade que está em nós, e para sempre estará conosco:</versiculo>
		<versiculo numero="3">Graça, misericórdia e paz, da parte de Deus Pai e da do Senhor Jesus Cristo, o Filho do Pai, seja convosco na verdade e amor.</versiculo>
		<versiculo numero="4">Muito me alegro por achar que alguns de teus filhos andam na verdade, assim como temos recebido o mandamento do Pai.</versiculo>
		<versiculo numero="5">E agora, senhora, rogo-te, não como escrevendo-te um novo mandamento, mas aquele mesmo que desde o princípio tivemos: que nos amemos uns aos outros.</versiculo>
		<versiculo numero="6">E o amor é este: que andemos segundo os seus mandamentos. Este é o mandamento, como já desde o princípio ouvistes, que andeis nele.</versiculo>
		<versiculo numero="7">Porque já muitos enganadores entraram no mundo, os quais não confessam que Jesus Cristo veio em carne. Este tal é o enganador e o anticristo.</versiculo>
		<versiculo numero="8">Olhai por vós mesmos, para que não percamos o que temos ganho, antes recebamos o inteiro galardão.</versiculo>
		<versiculo numero="9">Todo aquele que prevarica, e não persevera na doutrina de Cristo, não tem a Deus. Quem persevera na doutrina de Cristo, esse tem tanto ao Pai como ao Filho.</versiculo>
		<versiculo numero="10">Se alguém vem ter convosco, e não traz esta doutrina, não o recebais em casa, nem tampouco o saudeis.</versiculo>
		<versiculo numero="11">Porque quem o saúda tem parte nas suas más obras.</versiculo>
		<versiculo numero="12">Tendo muito que escrever-vos, não quis fazê-lo com papel e tinta; mas espero ir ter convosco e falar face a face, para que o nosso gozo seja cumprido.</versiculo>
		<versiculo numero="13">Saúdam-te os filhos de tua irmã, a eleita. Amém.</versiculo>
	</capitulo>
</livro>